<?xml version="1.0" encoding="UTF-8"?>
<!DOCTYPE peripheralPage SYSTEM "_menu.dtd" >
<!-- cmp0_trigm.xml -->

<peripheralPage xmlns:xi="http://www.w3.org/2001/XInclude" name="_instance" description="Comparitor">
 
   <template key="/CMP0/InternalInputMapping" namespace="all"><![CDATA[
   \t// cmp0_trigm.xml
   \tCmp0Input_Dac1       = Cmp0Input_4, //!< 12-bit DAC1 Output
   \tCmp0Input_VRefOut    = Cmp0Input_5, //!< Vref Output
   \tCmp0Input_Bandgap    = Cmp0Input_6, //!< Internal Band-gap
   \tCmp0Input_Cmp0Dac    = Cmp0Input_7, //!< CMP0 6-bit internal DAC reference
   ]]></template>
   
   <template key="/CMP1/InternalInputMapping" namespace="all"><![CDATA[
   \t// cmp0_trigm.xml
   \tCmp1Input_Dac0       = Cmp1Input_3, //!< 12-bit DAC0 Output
   \tCmp1Input_VRefOut    = Cmp1Input_5, //!< Vref Output
   \tCmp1Input_Bandgap    = Cmp1Input_6, //!< Internal Band-gap
   \tCmp1Input_Cmp1Dac    = Cmp1Input_7, //!< CMP1 6-bit internal DAC reference
   ]]></template>
 
   <xi:include href="cmp_base.xml"/>
 
   <choiceOption key="cmp_muxcr_psel" 
      description="Plus Input Mux Control"
      toolTip="Determines which input is selected for the plus input of the comparator" >
      <choice value="0" name="CMP_IN0" />
      <choice value="1" name="CMP_IN1" />
      <choice value="2" name="CMP_IN2" />
      <choice value="3" name="CMP_IN3" />
      <choice value="4" name="CMP_IN4/12-bit DAC1" />
      <choice value="5" name="CMP_IN5/VREF_OUT" />
      <choice value="6" name="Bandgap" />
      <choice value="7" name="6-bit DAC" />
   </choiceOption>

   <choiceOption key="cmp_muxcr_msel" 
      description="Minus Input Mux Control"
      toolTip="Determines which input is selected for the minus input of the comparator" >
      <choice value="0" name="CMP_IN0" />
      <choice value="1" name="CMP_IN1" />
      <choice value="2" name="CMP_IN2" />
      <choice value="3" name="CMP_IN3" />
      <choice value="4" name="CMP_IN4/12-bit DAC1" />
      <choice value="5" name="CMP_IN5/VREF_OUT" />
      <choice value="6" name="Bandgap" />
      <choice value="7" name="6-bit DAC" />
   </choiceOption>

   <template><![CDATA[
      \t//! MUX Control Register
      \tstatic constexpr uint32_t muxcr =
      \t   CMP_MUXCR_PSEL($(cmp_muxcr_psel))| // Plus Input Mux Control
      \t   CMP_MUXCR_MSEL($(cmp_muxcr_msel)); // Minus Input Mux Control\n\n
   ]]></template>

   <xi:include href="_clockOption.xml"/>

   <xi:include href="_irqOption.xml"/>         

   <signals/>
   
</peripheralPage>
